txn_harvester/__init__.py
txn_harvester/main.py
txn_harvester/prompts.py
txn_harvester-2025.12.22084352.dist-info/METADATA
txn_harvester-2025.12.22084352.dist-info/WHEEL
txn_harvester-2025.12.22084352.dist-info/top_level.txt
txn_harvester-2025.12.22084352.dist-info/RECORD
