Metadata-Version: 2.4
Name: txn-harvester
Version: 2025.12.22084352
Summary: txn-harvester extracts and structures financial transaction data from unstructured text, parsing amounts, dates, and categories for automation.
Author-email: txn-harvester <hi@eugene.plus>
License: MIT
Project-URL: Homepage, https://github.com/chigwell/txn-harvester
Requires-Python: >=3.9
Requires-Dist: langchain-llm7>=0.0.0
Requires-Dist: llmatch-messages>=0.0.0
Requires-Dist: langchain-core>=0.3.0
